adv_tools/__init__.py
adv_tools/logger.py
adv_tools-0.1.1.dist-info/METADATA
adv_tools-0.1.1.dist-info/WHEEL
adv_tools-0.1.1.dist-info/RECORD
